autoz/__init__.py
autoz/kit.py
autoz-0.0.1.dist-info/LICENSE
autoz-0.0.1.dist-info/METADATA
autoz-0.0.1.dist-info/WHEEL
autoz-0.0.1.dist-info/top_level.txt
autoz-0.0.1.dist-info/RECORD
