Metadata-Version: 2.1
Name: autoz
Version: 0.0.1
Summary: web automation tool selenium based
Author-email: Aston Kariuki <astonmwendwa254@gmail.com>
Classifier: Programming Language :: Python :: 3
Classifier: License :: OSI Approved :: MIT License
Classifier: Operating System :: OS Independent
Requires-Python: >=3.8
License-File: LICENSE
Requires-Dist: cryptography
Requires-Dist: selenium
Requires-Dist: encron
